parse_schema_validator
